rtl/blinker.sv
module blinker (
    input  logic clk,
    input  logic rst_n,
    output logic led
);
    always_ff @(posedge clk or negedge rst_n) begin
        if (!rst_n) led <= 1'b0;
        else        led <= ~led;
    end
endmodule

tb/blinker_tb.sv
module blinker_tb;
    logic clk = 0;
    logic rst_n = 0;
    logic led;

    blinker dut (.clk(clk), .rst_n(rst_n), .led(led));

    always #5 clk = ~clk;

    initial begin
        $dumpfile("sim/m0_smoke_test/blinker.vcd");
        $dumpvars(0, blinker_tb);

        rst_n = 0;
        #12 rst_n = 1;
        #100 $finish;
    end
endmodule

sim/m0_smoke_test/blinker.vcd
$date
	Mon Sep 14 19:59:35 2026
$end
$version
	Icarus Verilog
$end
$timescale
	1s
$end
$scope module blinker_tb $end
$var wire 1 ! led $end
$var reg 1 " clk $end
$var reg 1 # rst_n $end
$scope module dut $end
$var wire 1 " clk $end
$var wire 1 # rst_n $end
$var reg 1 ! led $end
$upscope $end
$upscope $end
$enddefinitions $end
$comment Show the parameter values. $end
$dumpall
$end
#0
$dumpvars
0#
0"
x!
$end
#5
0!
1"
#10
0"
#12
1#
#15
1!
1"
#20
0"
#25
0!
1"
#30
0"
#35
1!
1"
#40
0"
#45
0!
1"
#50
0"
#55
1!
1"
#60
0"
#65
0!
1"
#70
0"
#75
1!
1"
#80
0"
#85
0!
1"
#90
0"
#95
1!
1"
#100
0"
#105
0!
1"
